ptgaze/__init__.py
ptgaze/__main__.py
ptgaze/demo.py
ptgaze/gaze_estimator.py
ptgaze/main.py
ptgaze/transforms.py
ptgaze/utils.py
ptgaze/common/__init__.py
ptgaze/common/camera.py
ptgaze/common/eye.py
ptgaze/common/face.py
ptgaze/common/face_model.py
ptgaze/common/face_model_68.py
ptgaze/common/face_model_mediapipe.py
ptgaze/common/face_parts.py
ptgaze/common/visualizer.py
ptgaze/data/calib/sample_params.yaml
ptgaze/data/configs/eth-xgaze.yaml
ptgaze/data/configs/mpiifacegaze.yaml
ptgaze/data/configs/mpiigaze.yaml
ptgaze/data/normalized_camera_params/eth-xgaze.yaml
ptgaze/data/normalized_camera_params/mpiifacegaze.yaml
ptgaze/data/normalized_camera_params/mpiigaze.yaml
ptgaze/head_pose_estimation/__init__.py
ptgaze/head_pose_estimation/face_landmark_estimator.py
ptgaze/head_pose_estimation/head_pose_normalizer.py
ptgaze/models/__init__.py
ptgaze/models/mpiifacegaze/__init__.py
ptgaze/models/mpiifacegaze/resnet_simple.py
ptgaze/models/mpiifacegaze/backbones/__init__.py
ptgaze/models/mpiifacegaze/backbones/resnet_simple.py
ptgaze/models/mpiigaze/__init__.py
ptgaze/models/mpiigaze/resnet_preact.py
ptgaze-0.2.8.dist-info/LICENSE
ptgaze-0.2.8.dist-info/METADATA
ptgaze-0.2.8.dist-info/WHEEL
ptgaze-0.2.8.dist-info/entry_points.txt
ptgaze-0.2.8.dist-info/top_level.txt
ptgaze-0.2.8.dist-info/RECORD
