Metadata-Version: 2.1
Name: ptgaze
Version: 0.2.8
Summary: Gaze estimation using MPIIGaze and MPIIFaceGaze
Home-page: https://github.com/hysts/pytorch_mpiigaze_demo
Author: hysts
Requires-Python: >=3.7
License-File: LICENSE
Requires-Dist: dlib
Requires-Dist: face-alignment
Requires-Dist: mediapipe
Requires-Dist: numpy
Requires-Dist: omegaconf
Requires-Dist: opencv-python
Requires-Dist: pyyaml
Requires-Dist: scipy
Requires-Dist: timm
Requires-Dist: torch
Requires-Dist: torchvision
